reverpf/__init__.py
reverpf/reverpf.py
reverpf-0.6.1.dist-info/DESCRIPTION.rst
reverpf-0.6.1.dist-info/METADATA
reverpf-0.6.1.dist-info/RECORD
reverpf-0.6.1.dist-info/WHEEL
reverpf-0.6.1.dist-info/entry_points.txt
reverpf-0.6.1.dist-info/metadata.json
reverpf-0.6.1.dist-info/top_level.txt
tests/__init__.py
tests/test_cli_options.py
tests/test_reverse_printf.py
