Metadata-Version: 2.0
Name: reverpf
Version: 0.6.1
Summary: Reverse Printf
Home-page: https://bitbucket.com/penicolas/reverpf
Author: penicolas
Author-email: png1981@gmail.com
License: UNKNOWN
Platform: UNKNOWN
Classifier: Programming Language :: Python
Classifier: Development Status :: 4 - Beta
Classifier: License :: OSI Approved :: MIT License
Classifier: Operating System :: OS Independent
Classifier: Programming Language :: Python :: 3 :: Only
Classifier: Topic :: Utilities
